README.rst
setup.cfg
setup.py
./__init__.py
./product.py
./product.xml
./tryton.cfg
./tests/__init__.py
./tests/test_product.py
./tests/test_views_depends.py
fio_product_elasticsearch.egg-info/PKG-INFO
fio_product_elasticsearch.egg-info/SOURCES.txt
fio_product_elasticsearch.egg-info/dependency_links.txt
fio_product_elasticsearch.egg-info/entry_points.txt
fio_product_elasticsearch.egg-info/not-zip-safe
fio_product_elasticsearch.egg-info/requires.txt
fio_product_elasticsearch.egg-info/top_level.txt